cat/__init__.py
cat/_version.py
test_cat_zhiweiHong-2.0.0.dist-info/COPYING.txt
test_cat_zhiweiHong-2.0.0.dist-info/METADATA
test_cat_zhiweiHong-2.0.0.dist-info/WHEEL
test_cat_zhiweiHong-2.0.0.dist-info/entry_points.txt
test_cat_zhiweiHong-2.0.0.dist-info/top_level.txt
test_cat_zhiweiHong-2.0.0.dist-info/RECORD
