Metadata-Version: 2.1
Name: test-cat-zhiweiHong
Version: 2.0.0
Summary: A simple Python package that provides functionalities related to cats.
Home-page: https://github.com/zhiweiHong/test-cat-zhiweihong
Author: zhiweiHong
Author-email: 970060150@qq.com
Classifier: License :: OSI Approved :: MIT License
Classifier: Programming Language :: Python :: 3
Classifier: Programming Language :: Python :: 3.6
Classifier: Programming Language :: Python :: 3.7
Classifier: Programming Language :: Python :: 3.8
Classifier: Programming Language :: Python :: 3.9
Classifier: Programming Language :: Python :: 3.10
License-File: COPYING.txt
